{
  "schemaVersion": 1,
  "id": "better-ecology-gametest",
  "version": "1.0.0",
  "name": "Better Ecology Game Tests",
  "environment": "*",
  "entrypoints": {
    "fabric-gametest": [
      "me.javavirtualenv.gametest.ThirstBehaviorTests",
      "me.javavirtualenv.gametest.HungerBehaviorTests",
      "me.javavirtualenv.gametest.FleeingBehaviorTests",
      "me.javavirtualenv.gametest.PredatorBehaviorTests",
      "me.javavirtualenv.gametest.CowBehaviorTests",
      "me.javavirtualenv.gametest.PigBehaviorTests",
      "me.javavirtualenv.gametest.ChickenBehaviorTests",
      "me.javavirtualenv.gametest.RabbitBehaviorTests",
      "me.javavirtualenv.gametest.FoxBehaviorTests",
      "me.javavirtualenv.gametest.WolfBehaviorTests",
      "me.javavirtualenv.gametest.BehavioralTests",
      "me.javavirtualenv.gametest.SheepBehaviorTests",
      "me.javavirtualenv.gametest.BreedingBehaviorTests",
      "me.javavirtualenv.gametest.ParentOffspringTests"
    ]
  },
  "depends": {
    "fabricloader": ">=0.18.4",
    "minecraft": "~1.21.1",
    "fabric": "*",
    "fabric-gametest-api-v1": "*",
    "better-ecology": "*"
  }
}
